monkey/__init__.py
monkey/crawler/__init__.py
monkey/crawler/rest/__init__.py
monkey/crawler/rest/crawlers/__init__.py
monkey/crawler/rest/crawlers/api.py
monkey.crawler.rest-0.1.0.dev1.dist-info/LICENSE.txt
monkey.crawler.rest-0.1.0.dev1.dist-info/METADATA
monkey.crawler.rest-0.1.0.dev1.dist-info/WHEEL
monkey.crawler.rest-0.1.0.dev1.dist-info/top_level.txt
monkey.crawler.rest-0.1.0.dev1.dist-info/RECORD
