Metadata-Version: 2.1
Name: monkey.crawler.rest
Version: 0.1.0.dev1
Home-page: https://bitbucket.org/monkey-python/monkey-crawler-rest/
Author: Xavier ROY
Author-email: Xavier ROY <xavier@regbuddy.eu>
License: Apache License
Project-URL: Repository, https://bitbucket.org/monkey-python/monkey-crawler-rest/
Classifier: Development Status :: 1 - Planning
Classifier: Operating System :: OS Independent
Classifier: Programming Language :: Python :: 3.10
Classifier: Topic :: Software Development :: Libraries :: Python Modules
Classifier: Intended Audience :: Developers
Requires-Python: >=3.10
License-File: LICENSE.txt
Requires-Dist: monkey.crawler >=2.0.0.dev7
Requires-Dist: requests
Requires-Dist: setuptools
